bbj/BJCardCount.py
bbj/BJCardCountQuiz.py
bbj/BJComps.py
bbj/BJCoplayer.py
bbj/BJDealer.py
bbj/BJDeck.py
bbj/BJException.py
bbj/BJGame.py
bbj/BJPlayerAction.py
bbj/BJRoundOutcome.py
bbj/BJRuleset.py
bbj/BJSeqOutcome.py
bbj/BJStrategy.py
bbj/Blackjack.py
bbj/Card.py
bbj/CasinoComp.py
bbj/Deck.py
bbj/Purse.py
bbj/Shoe.py
bbj/Waitstaff.py
bbj/__init__.py
bbj/__main__.py
bbj/metadata.py
bbj/money.py
bbj/peafowlterm.py
Benevolent_Blackjack-1.0.dist-info/COPYING
Benevolent_Blackjack-1.0.dist-info/METADATA
Benevolent_Blackjack-1.0.dist-info/WHEEL
Benevolent_Blackjack-1.0.dist-info/top_level.txt
Benevolent_Blackjack-1.0.dist-info/RECORD
