Metadata-Version: 2.1
Name: Benevolent-Blackjack
Version: 1.0
Summary: A console-based Blackjack program that can teach basic strategy and card-counting.
Home-page: https://github.com/philipmw/benevolent-blackjack
Author: Philip M. White
Author-email: philip@mailworks.org
License: Copyright (C) 2012 Philip M. White, licensed under the GNU General Public License version 3
Platform: UNKNOWN
Classifier: Environment :: Console
Classifier: Intended Audience :: End Users/Desktop
Classifier: License :: OSI Approved :: GNU General Public License v3 (GPLv3)
Classifier: Natural Language :: English
Classifier: Operating System :: OS Independent
Classifier: Topic :: Games/Entertainment
